{"type":{"type":"archive","data":{"item":{"type":{"type":"item","data":{"metadata":{"identifier":"Sahih_Al-Bukhari_ibn-Baz","mediatype":"audio","description":"لقراءة او تحميل كتاب صحيح البخاري :<small><a href=\"https://ia801009.us.archive.org/28/items/Sharh_Sahih_al_Bukhari/Sahih_Al-Bukhari.pdf\" rel=\"nofollow\"><big><big><big><b> اضغط هنا</b></big></big></big></a><br /><br /></small>PDF او حمّله من آخر الصفحة بصيغة<br />","title":"شرح صحيح البخاري","publicdate":"2014-01-11T08:23:49.000","addeddate":"2014-01-11T08:23:49.000"}}}}}},"groups":["-OJerXriuyTTb69CMTBv"],"collections":["main","-OJerXvKCplUUx-ptcKN"],"title":{"translations":{"en":"شرح صحيح البخاري","ar":"شرح صحيح البخاري"}},"description":{"translations":{"en":"العلامة ابن باز","ar":"العلامة ابن باز"}},"publishStatus":"published","createdAt":"2025-02-20T14:25:38.001275","updatedAt":"2025-02-20T14:25:38.001280","createdBy":{"email":"sha.kamel.eng@gmail.com","id":"7rD1JGJZ7Eg9nWzIYySMucJJqkv2","isAdmin":true},"isPromoted":false,"id":"cooknujjWmYcdq_ijmbjZ_oWdgnjIWcdcU0gh1pfcWmdUdXih1Wu"}